art/__init__.py
art/__main__.py
art/crawler.py
art/gitFinder.py
art/jsFinder.py
art/parameter.py
art/setup.py
art/subdomain.py
core/__init__.py
core/crawler.py
core/gitFinder.py
core/jsFinder.py
core/main.py
core/parameter.py
core/setup.py
core/subdomain.py
ART_Recon-0.0.1.dist-info/METADATA
ART_Recon-0.0.1.dist-info/WHEEL
ART_Recon-0.0.1.dist-info/top_level.txt
ART_Recon-0.0.1.dist-info/RECORD
